{"premium_type": "free", "content_ratings": null, "manifest_url": "https://marketplace.firefox.com/app/bb1d01d0-7c8e-4b55-a0e6-60e0ef70cd59/manifest.webapp", "current_version": "0.1", "upsold": null, "id": "454412", "ratings": {"count": 3, "average": 4.5}, "app_type": "packaged", "author": "Ibnu Yahya", "support_url": "http://anak10thn.web.id", "slug": "goflight", "regions": [{"mcc": 722, "name": "Argentina", "adolescent": true, "slug": "ar"}, {"mcc": 724, "name": "Brazil", "adolescent": true, "slug": "br"}, {"mcc": 460, "name": "China", "adolescent": true, "slug": "cn"}, {"mcc": 732, "name": "Colombia", "adolescent": true, "slug": "co"}, {"mcc": 262, "name": "Germany", "adolescent": true, "slug": "de"}, {"mcc": 214, "name": "Spain", "adolescent": true, "slug": "es"}, {"mcc": 202, "name": "Greece", "adolescent": true, "slug": "gr"}, {"mcc": 216, "name": "Hungary", "adolescent": true, "slug": "hu"}, {"mcc": 297, "name": "Montenegro", "adolescent": true, "slug": "me"}, {"mcc": 334, "name": "Mexico", "adolescent": true, "slug": "mx"}, {"mcc": 716, "name": "Peru", "adolescent": true, "slug": "pe"}, {"mcc": 260, "name": "Poland", "adolescent": true, "slug": "pl"}, {"mcc": 220, "name": "Serbia", "adolescent": true, "slug": "rs"}, {"mcc": 235, "name": "United Kingdom", "adolescent": true, "slug": "uk"}, {"mcc": 310, "name": "United States", "adolescent": true, "slug": "us"}, {"mcc": 748, "name": "Uruguay", "adolescent": true, "slug": "uy"}, {"mcc": 734, "name": "Venezuela", "adolescent": true, "slug": "ve"}, {"mcc": null, "name": "Worldwide", "adolescent": true, "slug": "worldwide"}], "icons": {"16": "https://marketplace.cdn.mozilla.net/img/uploads/addon_icons/454/454412-32.png?modified=1373667634", "48": "https://marketplace.cdn.mozilla.net/img/uploads/addon_icons/454/454412-48.png?modified=1373667634", "128": "https://marketplace.cdn.mozilla.net/img/uploads/addon_icons/454/454412-128.png?modified=1373667634", "64": "https://marketplace.cdn.mozilla.net/img/uploads/addon_icons/454/454412-64.png?modified=1373667634"}, "created": "2013-07-12T14:56:48", "homepage": "http://anak10thn.web.id", "support_email": "anak10thn@gmail.com", "public_stats": false, "status": 4, "privacy_policy": "/api/v1/apps/app/454412/privacy/", "is_packaged": true, "description": "Indonesian Tiket Tracking", "default_locale": "en-US", "tags": [], "price": null, "previews": [{"filetype": "image/png", "thumbnail_url": "https://marketplace.cdn.mozilla.net/img/uploads/previews/thumbs/107/107536.png?modified=1373666484", "image_url": "https://marketplace.cdn.mozilla.net/img/uploads/previews/full/107/107536.png?modified=1373666484", "id": "107536", "resource_uri": "/api/v1/apps/preview/107536/"}, {"filetype": "image/png", "thumbnail_url": "https://marketplace.cdn.mozilla.net/img/uploads/previews/thumbs/107/107538.png?modified=1373666484", "image_url": "https://marketplace.cdn.mozilla.net/img/uploads/previews/full/107/107538.png?modified=1373666484", "id": "107538", "resource_uri": "/api/v1/apps/preview/107538/"}, {"filetype": "image/png", "thumbnail_url": "https://marketplace.cdn.mozilla.net/img/uploads/previews/thumbs/107/107540.png?modified=1373666484", "image_url": "https://marketplace.cdn.mozilla.net/img/uploads/previews/full/107/107540.png?modified=1373666484", "id": "107540", "resource_uri": "/api/v1/apps/preview/107540/"}], "payment_account": null, "categories": ["travel"], "supported_locales": ["id"], "price_locale": null, "name": "GoFlight", "versions": {"0.1": "/api/v1/apps/versions/1474340/"}, "device_types": ["firefoxos"], "payment_required": false, "weekly_downloads": null, "upsell": false, "resource_uri": "/api/v1/apps/app/454412/"}