{"app_type": "hosted", "author": "Dimitris Gardiklis", "banner_message": null, "banner_regions": [], "categories": ["business", "utilities"], "content_ratings": {"regions": {"uy": "esrb", "gr": "pegi", "cl": "esrb", "de": "usk", "it": "pegi", "us": "esrb", "hu": "pegi", "br": "classind", "ar": "esrb", "es": "pegi", "uk": "pegi", "pe": "esrb", "co": "esrb", "mx": "esrb", "pl": "pegi", "ve": "esrb"}, "ratings": null, "interactive_elements": null, "descriptors": null}, "created": "2012-10-20T15:35:10", "current_version": "1.006", "default_locale": "en-US", "description": {"en-US": "sunNshadow is a tool for calculating sun azimuth and altitude at any given time. It can also determine if a shadow is cast from a specified obstacle.\n<b> SunNShadow </b>\nThis is a tool for calculating sun azimuth and altitude at any given time. It can also determine if a shadow is cast from a specified obstacle.\n\n<b>Sun position</b>\n In the beginning the latitude, longitude and current time are automatically set. Then by moving any slider or inputting any value, the results are presented in the appropriate fields.\n\n<b>Shadow </b>\nIn the fields obstacle distance and height, the values for the obstacle are declared. In the \u201csun shadow\u201d field the difference between the distance from the obstacle and the shadow length is calculated for the specified time. If the difference is &lt; 0 then the shadow overlaps the calculation point.\n\n<b>Batch shadow calculation</b>\n By pressing the button \"calculation per hour and month\" the shadow is calculated for every hour and month. A list is printed for the times when the shadow reaches the calculation point."}, "device_types": ["desktop", "android-mobile", "android-tablet", "firefoxos"], "homepage": {"en-US": "http://mc96107.github.io/sunNshadow"}, "icons": {"16": "https://marketplace.cdn.mozilla.net/img/uploads/addon_icons/403/403662-32.png?modified=1366295528", "48": "https://marketplace.cdn.mozilla.net/img/uploads/addon_icons/403/403662-48.png?modified=1366295528", "128": "https://marketplace.cdn.mozilla.net/img/uploads/addon_icons/403/403662-128.png?modified=1366295528", "64": "https://marketplace.cdn.mozilla.net/img/uploads/addon_icons/403/403662-64.png?modified=1366295528"}, "id": 403662, "is_packaged": false, "manifest_url": "http://mc96107.github.io/sunNshadow/manifest.webapp", "name": {"en-US": "sunNshadow"}, "payment_account": null, "payment_required": false, "premium_type": "free", "previews": [{"filetype": "image/png", "image_url": "https://marketplace.cdn.mozilla.net/img/uploads/previews/full/80/80316.png?modified=1350821035", "id": 80316, "resource_uri": null, "thumbnail_url": "https://marketplace.cdn.mozilla.net/img/uploads/previews/thumbs/80/80316.png?modified=1350821035"}], "price": null, "price_locale": null, "privacy_policy": "/api/v1/apps/app/403662/privacy/", "public_stats": false, "release_notes": null, "ratings": {"count": 0, "average": 0.0}, "regions": [{"name": "Argentina", "slug": "ar", "mcc": 722, "adolescent": true}, {"name": "Brazil", "slug": "br", "mcc": 724, "adolescent": true}, {"name": "Chile", "slug": "cl", "mcc": 730, "adolescent": true}, {"name": "Colombia", "slug": "co", "mcc": 732, "adolescent": true}, {"name": "Germany", "slug": "de", "mcc": 262, "adolescent": true}, {"name": "Spain", "slug": "es", "mcc": 214, "adolescent": true}, {"name": "Greece", "slug": "gr", "mcc": 202, "adolescent": true}, {"name": "Hungary", "slug": "hu", "mcc": 216, "adolescent": true}, {"name": "Italy", "slug": "it", "mcc": 222, "adolescent": true}, {"name": "Montenegro", "slug": "me", "mcc": 297, "adolescent": true}, {"name": "Mexico", "slug": "mx", "mcc": 334, "adolescent": true}, {"name": "Peru", "slug": "pe", "mcc": 716, "adolescent": true}, {"name": "Poland", "slug": "pl", "mcc": 260, "adolescent": true}, {"name": "Serbia", "slug": "rs", "mcc": 220, "adolescent": true}, {"name": "United Kingdom", "slug": "uk", "mcc": 235, "adolescent": true}, {"name": "United States", "slug": "us", "mcc": 310, "adolescent": true}, {"name": "Uruguay", "slug": "uy", "mcc": 748, "adolescent": true}, {"name": "Venezuela", "slug": "ve", "mcc": 734, "adolescent": true}, {"name": "Worldwide", "slug": "worldwide", "mcc": null, "adolescent": true}], "resource_uri": "/api/v1/apps/app/403662/", "slug": "sunnshadow", "status": 4, "summary": null, "support_email": {"en-US": "mc96107+sunNshadow@gmail.com"}, "support_url": {"en-US": "https://github.com/mc96107/sunNshadow"}, "supported_locales": [], "tags": [], "upsell": false, "upsold": null, "user": null, "versions": {"1.006": "/api/v1/apps/versions/1388814/"}, "weekly_downloads": null}