{"app_type": "hosted", "author": "TweenSoft Inc.", "categories": ["games"], "content_ratings": {"ratings": {"de": {"body": "Generic", "body_label": "generic", "description": "Not recommended for users younger than 12 years of age", "rating_label": "12", "rating": "For ages 12+"}, "br": {"body": "CLASSIND", "body_label": "classind", "description": "Not recommended for users younger than 14 years of age", "rating_label": "14", "rating": "For ages 14+"}}, "interactive_elements": null, "descriptors": null}, "created": "2013-01-16T00:57:36", "current_version": "1.0", "default_locale": "en-US", "device_types": ["desktop", "android-mobile", "firefoxos"], "description": {"en-US": "If you are feeling lucky, then try this game! This game is highly addictive and is fun for hours! Play everyday and hit the jackpot, big time."}, "homepage": {"en-US": ""}, "icons": {"16": "https://marketplace.cdn.mozilla.net/img/uploads/addon_icons/416/416790-32.png?modified=1381881747", "48": "https://marketplace.cdn.mozilla.net/img/uploads/addon_icons/416/416790-48.png?modified=1381881747", "128": "https://marketplace.cdn.mozilla.net/img/uploads/addon_icons/416/416790-128.png?modified=1381881747", "64": "https://marketplace.cdn.mozilla.net/img/uploads/addon_icons/416/416790-64.png?modified=1381881747"}, "id": 416790, "is_packaged": false, "manifest_url": "http://videopoker.justplaymobile.com/videopoker.webapp", "name": {"en-US": "Video Poker"}, "payment_account": null, "payment_required": false, "premium_type": "free", "previews": [{"filetype": "image/png", "image_url": "https://marketplace.cdn.mozilla.net/img/uploads/previews/full/87/87560.png?modified=1358395661", "id": 87560, "resource_uri": null, "thumbnail_url": "https://marketplace.cdn.mozilla.net/img/uploads/previews/thumbs/87/87560.png?modified=1358395661"}, {"filetype": "image/png", "image_url": "https://marketplace.cdn.mozilla.net/img/uploads/previews/full/87/87562.png?modified=1358395660", "id": 87562, "resource_uri": null, "thumbnail_url": "https://marketplace.cdn.mozilla.net/img/uploads/previews/thumbs/87/87562.png?modified=1358395660"}, {"filetype": "image/png", "image_url": "https://marketplace.cdn.mozilla.net/img/uploads/previews/full/87/87564.png?modified=1358395660", "id": 87564, "resource_uri": null, "thumbnail_url": "https://marketplace.cdn.mozilla.net/img/uploads/previews/thumbs/87/87564.png?modified=1358395660"}, {"filetype": "image/png", "image_url": "https://marketplace.cdn.mozilla.net/img/uploads/previews/full/87/87566.png?modified=1358395661", "id": 87566, "resource_uri": null, "thumbnail_url": "https://marketplace.cdn.mozilla.net/img/uploads/previews/thumbs/87/87566.png?modified=1358395661"}], "price": null, "price_locale": null, "privacy_policy": "/api/v1/apps/app/416790/privacy/", "public_stats": false, "ratings": {"count": 0, "average": 0.0}, "regions": [{"name": "Argentina", "slug": "ar", "mcc": 722, "adolescent": true}, {"name": "Brazil", "slug": "br", "mcc": 724, "adolescent": true}, {"name": "Colombia", "slug": "co", "mcc": 732, "adolescent": true}, {"name": "Germany", "slug": "de", "mcc": 262, "adolescent": true}, {"name": "Spain", "slug": "es", "mcc": 214, "adolescent": true}, {"name": "Greece", "slug": "gr", "mcc": 202, "adolescent": true}, {"name": "Hungary", "slug": "hu", "mcc": 216, "adolescent": true}, {"name": "Italy", "slug": "it", "mcc": 222, "adolescent": true}, {"name": "Montenegro", "slug": "me", "mcc": 297, "adolescent": true}, {"name": "Mexico", "slug": "mx", "mcc": 334, "adolescent": true}, {"name": "Peru", "slug": "pe", "mcc": 716, "adolescent": true}, {"name": "Poland", "slug": "pl", "mcc": 260, "adolescent": true}, {"name": "Serbia", "slug": "rs", "mcc": 220, "adolescent": true}, {"name": "United Kingdom", "slug": "uk", "mcc": 235, "adolescent": true}, {"name": "United States", "slug": "us", "mcc": 310, "adolescent": true}, {"name": "Uruguay", "slug": "uy", "mcc": 748, "adolescent": true}, {"name": "Venezuela", "slug": "ve", "mcc": 734, "adolescent": true}, {"name": "Worldwide", "slug": "worldwide", "mcc": null, "adolescent": true}], "release_notes": null, "resource_uri": "/api/v1/apps/app/416790/", "slug": "video-poker", "status": 4, "summary": null, "support_email": {"en-US": "support@tweensoft.com"}, "support_url": {"en-US": "http://www.tweensoft.com"}, "supported_locales": [], "tags": [], "upsell": false, "upsold": null, "user": null, "versions": {"1.0": "/api/v1/apps/versions/1413202/"}, "weekly_downloads": null, "guid": "b2a7799a-9d53-4994-9625-3159462f6800", "app_slug": "video-poker", "type": 11, "highest_status": 13, "icon_type": "image/png", "developer_comments": null, "eula": null, "the_reason": null, "the_future": null, "average_rating": 0.0, "bayesian_rating": 0.0, "total_reviews": 0, "total_downloads": 0, "hotness": 0.0, "average_daily_downloads": 0, "average_daily_users": 0, "share_count": 0, "disabled_by_user": false, "trusted": false, "view_source": true, "prerelease": false, "admin_review": false, "admin_review_type": 1, "site_specific": false, "external_software": false, "dev_agreement": false, "auto_repackage": true, "outstanding": false, "target_locale": null, "locale_disambiguation": null, "wants_contributions": false, "paypal_id": "", "suggested_amount": null, "total_contributions": null, "annoying": 0, "enable_thankyou": false, "thankyou_note": null, "app_domain": "http://videopoker.justplaymobile.com", "mozilla_contact": "telin@mozilla.com", "enable_new_regions": true, "authors": [6120992], "dependencies": []}