{"app_type": "hosted", "author": "Yofie Setiawan", "banner_message": null, "banner_regions": [], "categories": ["productivity", "utilities"], "content_ratings": {"regions": {"uy": "esrb", "gr": "pegi", "cl": "esrb", "de": "usk", "it": "pegi", "us": "esrb", "hu": "pegi", "br": "classind", "ar": "esrb", "es": "pegi", "uk": "pegi", "pe": "esrb", "co": "esrb", "mx": "esrb", "pl": "pegi", "ve": "esrb"}, "ratings": null, "interactive_elements": null, "descriptors": null}, "created": "2013-08-15T14:19:02", "current_version": "1.0", "default_locale": "en-US", "description": {"en-US": "Vepom, an app to help you to check your vehicle gas performance. It might look confusing at first, but it's actually simple. Have you ever wonder, how far your car can run for 1 liter of gas? I usually compare my car gas performance when driving out of town which have very great traffic, and when i drive inside town, which usually have bad traffic. And yes, my car can run about 11KM/liter when driving out of town, and when inside town my car usually only can run about 9KM/liter. You just need to input 4 data to get result. This app have a little rule, you must use this app whenever you fill your gas in full-tank. So KM1 is your KM when last time you fill your gas in full-tank. While KM2 is your KM right now when you fill your gas in full-tank again."}, "device_types": ["desktop", "android-mobile", "android-tablet", "firefoxos"], "homepage": {"en-US": "http://vepom.yopdesign.com/index2.html"}, "icons": {"16": "https://marketplace.cdn.mozilla.net/img/uploads/addon_icons/460/460336-32.png?modified=1376602011", "48": "https://marketplace.cdn.mozilla.net/img/uploads/addon_icons/460/460336-48.png?modified=1376602011", "128": "https://marketplace.cdn.mozilla.net/img/uploads/addon_icons/460/460336-128.png?modified=1376602011", "64": "https://marketplace.cdn.mozilla.net/img/uploads/addon_icons/460/460336-64.png?modified=1376602011"}, "id": 460336, "is_packaged": false, "manifest_url": "http://vepom.yopdesign.com/manifest.webapp", "name": {"en-US": "Vepom"}, "payment_account": null, "payment_required": false, "premium_type": "free", "previews": [{"filetype": "image/png", "image_url": "https://marketplace.cdn.mozilla.net/img/uploads/previews/full/110/110956.png?modified=1376602011", "id": 110956, "resource_uri": null, "thumbnail_url": "https://marketplace.cdn.mozilla.net/img/uploads/previews/thumbs/110/110956.png?modified=1376602011"}, {"filetype": "image/png", "image_url": "https://marketplace.cdn.mozilla.net/img/uploads/previews/full/110/110957.png?modified=1376602011", "id": 110957, "resource_uri": null, "thumbnail_url": "https://marketplace.cdn.mozilla.net/img/uploads/previews/thumbs/110/110957.png?modified=1376602011"}, {"filetype": "image/png", "image_url": "https://marketplace.cdn.mozilla.net/img/uploads/previews/full/110/110958.png?modified=1376602011", "id": 110958, "resource_uri": null, "thumbnail_url": "https://marketplace.cdn.mozilla.net/img/uploads/previews/thumbs/110/110958.png?modified=1376602011"}], "price": null, "price_locale": null, "privacy_policy": "/api/v1/apps/app/460336/privacy/", "public_stats": false, "release_notes": null, "ratings": {"count": 0, "average": 0.0}, "regions": [{"name": "Argentina", "slug": "ar", "mcc": 722, "adolescent": true}, {"name": "Brazil", "slug": "br", "mcc": 724, "adolescent": true}, {"name": "Chile", "slug": "cl", "mcc": 730, "adolescent": true}, {"name": "Colombia", "slug": "co", "mcc": 732, "adolescent": true}, {"name": "Germany", "slug": "de", "mcc": 262, "adolescent": true}, {"name": "Spain", "slug": "es", "mcc": 214, "adolescent": true}, {"name": "Greece", "slug": "gr", "mcc": 202, "adolescent": true}, {"name": "Hungary", "slug": "hu", "mcc": 216, "adolescent": true}, {"name": "Italy", "slug": "it", "mcc": 222, "adolescent": true}, {"name": "Montenegro", "slug": "me", "mcc": 297, "adolescent": true}, {"name": "Mexico", "slug": "mx", "mcc": 334, "adolescent": true}, {"name": "Peru", "slug": "pe", "mcc": 716, "adolescent": true}, {"name": "Poland", "slug": "pl", "mcc": 260, "adolescent": true}, {"name": "Serbia", "slug": "rs", "mcc": 220, "adolescent": true}, {"name": "United Kingdom", "slug": "uk", "mcc": 235, "adolescent": true}, {"name": "United States", "slug": "us", "mcc": 310, "adolescent": true}, {"name": "Uruguay", "slug": "uy", "mcc": 748, "adolescent": true}, {"name": "Venezuela", "slug": "ve", "mcc": 734, "adolescent": true}, {"name": "Worldwide", "slug": "worldwide", "mcc": null, "adolescent": true}], "resource_uri": "/api/v1/apps/app/460336/", "slug": "vepom", "status": 4, "summary": null, "support_email": {"en-US": "yofie@yopdesign.com"}, "support_url": {"en-US": "http://www.yopdesign.com/blog/mozilla/388-vepom-vehicle-gas-performance-my-very-first-mobile-and-firefox-os-app.html"}, "supported_locales": [], "tags": [], "upsell": false, "upsold": null, "user": null, "versions": {"1.0": "/api/v1/apps/versions/1482817/"}, "weekly_downloads": null}