{"app_type": "hosted", "author": "NYPL Labs", "categories": ["education", "maps-navigation"], "content_ratings": {"ratings": null, "interactive_elements": null, "descriptors": null}, "created": "2013-10-22T15:28:33", "current_version": "1.0", "default_locale": "en-US", "device_types": ["desktop", "android-mobile", "android-tablet", "firefoxos"], "description": {"en-US": "Kill Time, Make History with the NYPL Labs Building Inspector. The New York Public Library is training computers how to recognize building shapes and other information from old city maps. Help us clean up the data so that it can be used in research, teaching and civic hacking."}, "homepage": {"en-US": ""}, "icons": {"16": "https://marketplace.cdn.mozilla.net/img/uploads/addon_icons/468/468820-32.png?modified=1383681335", "48": "https://marketplace.cdn.mozilla.net/img/uploads/addon_icons/468/468820-48.png?modified=1383681335", "128": "https://marketplace.cdn.mozilla.net/img/uploads/addon_icons/468/468820-128.png?modified=1383681335", "64": "https://marketplace.cdn.mozilla.net/img/uploads/addon_icons/468/468820-64.png?modified=1383681335"}, "id": 468820, "is_packaged": false, "manifest_url": "http://buildinginspector.nypl.org/firefox.webapp", "name": {"en-US": "BldgInspector by NYPL Labs"}, "payment_account": null, "payment_required": false, "premium_type": "free", "previews": [{"filetype": "image/png", "image_url": "https://marketplace.cdn.mozilla.net/img/uploads/previews/full/116/116163.png?modified=1382481725", "id": 116163, "resource_uri": null, "thumbnail_url": "https://marketplace.cdn.mozilla.net/img/uploads/previews/thumbs/116/116163.png?modified=1382481725"}, {"filetype": "image/png", "image_url": "https://marketplace.cdn.mozilla.net/img/uploads/previews/full/116/116165.png?modified=1382481726", "id": 116165, "resource_uri": null, "thumbnail_url": "https://marketplace.cdn.mozilla.net/img/uploads/previews/thumbs/116/116165.png?modified=1382481726"}], "price": null, "price_locale": null, "privacy_policy": "/api/v1/apps/app/468820/privacy/", "public_stats": false, "ratings": {"count": 0, "average": 0.0}, "regions": [{"name": "Argentina", "slug": "ar", "mcc": 722, "adolescent": true}, {"name": "Brazil", "slug": "br", "mcc": 724, "adolescent": true}, {"name": "Colombia", "slug": "co", "mcc": 732, "adolescent": true}, {"name": "Germany", "slug": "de", "mcc": 262, "adolescent": true}, {"name": "Spain", "slug": "es", "mcc": 214, "adolescent": true}, {"name": "Greece", "slug": "gr", "mcc": 202, "adolescent": true}, {"name": "Hungary", "slug": "hu", "mcc": 216, "adolescent": true}, {"name": "Italy", "slug": "it", "mcc": 222, "adolescent": true}, {"name": "Montenegro", "slug": "me", "mcc": 297, "adolescent": true}, {"name": "Mexico", "slug": "mx", "mcc": 334, "adolescent": true}, {"name": "Peru", "slug": "pe", "mcc": 716, "adolescent": true}, {"name": "Poland", "slug": "pl", "mcc": 260, "adolescent": true}, {"name": "Serbia", "slug": "rs", "mcc": 220, "adolescent": true}, {"name": "United Kingdom", "slug": "uk", "mcc": 235, "adolescent": true}, {"name": "United States", "slug": "us", "mcc": 310, "adolescent": true}, {"name": "Uruguay", "slug": "uy", "mcc": 748, "adolescent": true}, {"name": "Venezuela", "slug": "ve", "mcc": 734, "adolescent": true}, {"name": "Worldwide", "slug": "worldwide", "mcc": null, "adolescent": true}], "release_notes": null, "resource_uri": "/api/v1/apps/app/468820/", "slug": "bldginspector-by-nypl-labs", "status": 4, "summary": null, "support_email": {"en-US": "buildinginspector@nypl.org"}, "support_url": {"en-US": ""}, "supported_locales": [], "tags": [], "upsell": false, "upsold": null, "user": null, "versions": {"1.0": "/api/v1/apps/versions/1495428/"}, "weekly_downloads": null, "guid": "cb2d2e9d-9cb0-43a2-8590-6a523b34807f", "app_slug": "bldginspector-by-nypl-labs", "type": 11, "highest_status": 4, "icon_type": "image/png", "developer_comments": null, "eula": null, "the_reason": null, "the_future": null, "average_rating": 0.0, "bayesian_rating": 0.0, "total_reviews": 0, "total_downloads": 0, "hotness": 0.0, "average_daily_downloads": 0, "average_daily_users": 0, "share_count": 0, "disabled_by_user": false, "trusted": false, "view_source": true, "prerelease": false, "admin_review": false, "admin_review_type": 1, "site_specific": false, "external_software": false, "dev_agreement": false, "auto_repackage": true, "outstanding": false, "target_locale": null, "locale_disambiguation": null, "wants_contributions": false, "paypal_id": "", "suggested_amount": null, "total_contributions": null, "annoying": 0, "enable_thankyou": false, "thankyou_note": null, "app_domain": "http://buildinginspector.nypl.org", "mozilla_contact": "", "enable_new_regions": true, "authors": [10339544], "dependencies": []}