{"premium_type": "free", "content_ratings": null, "manifest_url": "http://beta.swartag.com/dinopanic/manifest.webapp", "current_version": {"developer_name": "Silverstore Games", "version": "1.0", "release_notes": null, "required_features": []}, "upsold": null, "id": "368149", "ratings": {"count": 1, "average": 1.0}, "app_type": "hosted", "icons": {"16": "https://marketplace.cdn.mozilla.net/img/uploads/addon_icons/368/368149-32.png?modified=1355340025", "48": "https://marketplace.cdn.mozilla.net/img/uploads/addon_icons/368/368149-48.png?modified=1355340025", "128": "https://marketplace.cdn.mozilla.net/img/uploads/addon_icons/368/368149-128.png?modified=1355340025", "64": "https://marketplace.cdn.mozilla.net/img/uploads/addon_icons/368/368149-64.png?modified=1355340025"}, "support_url": "", "slug": "dinopanic", "regions": [{"mcc": 732, "name": "Colombia", "adolescent": true, "slug": "co"}, {"mcc": 262, "name": "Germany", "adolescent": true, "slug": "de"}, {"mcc": 214, "name": "Spain", "adolescent": true, "slug": "es"}, {"mcc": 216, "name": "Hungary", "adolescent": true, "slug": "hu"}, {"mcc": 297, "name": "Montenegro", "adolescent": true, "slug": "me"}, {"mcc": 334, "name": "Mexico", "adolescent": true, "slug": "mx"}, {"mcc": 260, "name": "Poland", "adolescent": true, "slug": "pl"}, {"mcc": 220, "name": "Serbia", "adolescent": true, "slug": "rs"}, {"mcc": 235, "name": "United Kingdom", "adolescent": true, "slug": "uk"}, {"mcc": 310, "name": "United States", "adolescent": true, "slug": "us"}, {"mcc": 734, "name": "Venezuela", "adolescent": true, "slug": "ve"}, {"mcc": null, "name": "Worldwide", "adolescent": true, "slug": "worldwide"}], "homepage": "", "support_email": "", "public_stats": false, "status": 4, "privacy_policy": "/api/v1/apps/app/368149/privacy/", "is_packaged": false, "description": "A huge red T-REX is pissed off and it wants you for lunch. Escape the peril by sliding, running, jumping even gliding over obstacles while collecting gems for high scores at the same time!", "default_locale": "en-US", "listed_authors": [{"name": "Silverstore Games"}], "price": null, "previews": [{"filetype": "", "caption": "", "thumbnail_url": "https://marketplace.cdn.mozilla.net/img/uploads/previews/thumbs/68/68913.png?modified=1355164960", "image_url": "https://marketplace.cdn.mozilla.net/img/uploads/previews/full/68/68913.png?modified=1355164960", "id": "68913", "resource_uri": "/api/v1/apps/preview/68913/"}, {"filetype": "", "caption": "", "thumbnail_url": "https://marketplace.cdn.mozilla.net/img/uploads/previews/thumbs/68/68914.png?modified=1355164960", "image_url": "https://marketplace.cdn.mozilla.net/img/uploads/previews/full/68/68914.png?modified=1355164960", "id": "68914", "resource_uri": "/api/v1/apps/preview/68914/"}, {"filetype": "", "caption": "", "thumbnail_url": "https://marketplace.cdn.mozilla.net/img/uploads/previews/thumbs/68/68915.png?modified=1355164961", "image_url": "https://marketplace.cdn.mozilla.net/img/uploads/previews/full/68/68915.png?modified=1355164961", "id": "68915", "resource_uri": "/api/v1/apps/preview/68915/"}, {"filetype": "", "caption": "", "thumbnail_url": "https://marketplace.cdn.mozilla.net/img/uploads/previews/thumbs/68/68916.png?modified=1355164961", "image_url": "https://marketplace.cdn.mozilla.net/img/uploads/previews/full/68/68916.png?modified=1355164961", "id": "68916", "resource_uri": "/api/v1/apps/preview/68916/"}], "payment_account": null, "categories": [153, 155], "supported_locales": [], "price_locale": null, "name": "Dinopanic", "created": "2012-03-19T05:56:38", "device_types": ["desktop"], "payment_required": false, "weekly_downloads": null, "image_assets": {"featured_tile": ["https://marketplace.cdn.mozilla.net/img/uploads/imageassets/2/2850.png?modified=1349796978", 0], "mobile_tile": ["https://marketplace.cdn.mozilla.net/img/uploads/imageassets/0/542.png?modified=1346968320", 0], "desktop_tile": ["https://marketplace.cdn.mozilla.net/img/uploads/imageassets/0/552.png?modified=1346968320", 0]}, "upsell": false, "resource_uri": "/api/v1/apps/app/368149/"}