{"premium_type": "free", "content_ratings": null, "manifest_url": "http://lunchbug.lostdecadegames.com/mozillaMarketplace.json", "current_version": {"developer_name": "Lost Decade Games", "version": "1.20.25", "release_notes": "Hi Andrew. I've updated our manifest file and pushed the changes to our site. Let me know if there's anything else.", "required_features": []}, "upsold": null, "id": "383667", "ratings": {"count": 1, "average": 5.0}, "app_type": "hosted", "icons": {"16": "https://marketplace.cdn.mozilla.net/img/uploads/addon_icons/383/383667-32.png?modified=1359709605", "48": "https://marketplace.cdn.mozilla.net/img/uploads/addon_icons/383/383667-48.png?modified=1359709605", "128": "https://marketplace.cdn.mozilla.net/img/uploads/addon_icons/383/383667-128.png?modified=1359709605", "64": "https://marketplace.cdn.mozilla.net/img/uploads/addon_icons/383/383667-64.png?modified=1359709605"}, "support_url": "", "slug": "lunch-bug", "regions": [{"mcc": 732, "name": "Colombia", "adolescent": true, "slug": "co"}, {"mcc": 262, "name": "Germany", "adolescent": true, "slug": "de"}, {"mcc": 214, "name": "Spain", "adolescent": true, "slug": "es"}, {"mcc": 216, "name": "Hungary", "adolescent": true, "slug": "hu"}, {"mcc": 297, "name": "Montenegro", "adolescent": true, "slug": "me"}, {"mcc": 334, "name": "Mexico", "adolescent": true, "slug": "mx"}, {"mcc": 260, "name": "Poland", "adolescent": true, "slug": "pl"}, {"mcc": 220, "name": "Serbia", "adolescent": true, "slug": "rs"}, {"mcc": 235, "name": "United Kingdom", "adolescent": true, "slug": "uk"}, {"mcc": 310, "name": "United States", "adolescent": true, "slug": "us"}, {"mcc": 734, "name": "Venezuela", "adolescent": true, "slug": "ve"}, {"mcc": null, "name": "Worldwide", "adolescent": true, "slug": "worldwide"}], "homepage": "http://www.lunchbug.com", "support_email": "hello@lostdecadegames.com", "public_stats": false, "status": 4, "privacy_policy": "/api/v1/apps/app/383667/privacy/", "is_packaged": false, "description": "Feed the cute bugs in this strategic puzzle game!\nLunch Bug is the new HTML5 game from independent game studio Lost Decade Games. It's a unique, turn-based puzzle game featuring advanced strategy and endless gameplay. A free-to-play game, Lunch Bug utilizes Google Wallet to enable in-app purchase of in-game currency. Lunch Bug has been optimized to work in any modern browser, across desktop platforms (Linux, Mac, and Windows) as well as mobile devices including Android and iOS!", "default_locale": "en-US", "listed_authors": [], "price": null, "previews": [{"filetype": "image/png", "caption": "Title screen", "thumbnail_url": "https://marketplace.cdn.mozilla.net/img/uploads/previews/thumbs/88/88972.png?modified=1359738101", "image_url": "https://marketplace.cdn.mozilla.net/img/uploads/previews/full/88/88972.png?modified=1359738101", "id": "88972", "resource_uri": "/api/v1/apps/preview/88972/"}, {"filetype": "image/png", "caption": "Gameplay", "thumbnail_url": "https://marketplace.cdn.mozilla.net/img/uploads/previews/thumbs/88/88974.png?modified=1359738101", "image_url": "https://marketplace.cdn.mozilla.net/img/uploads/previews/full/88/88974.png?modified=1359738101", "id": "88974", "resource_uri": "/api/v1/apps/preview/88974/"}, {"filetype": "image/png", "caption": "Level select", "thumbnail_url": "https://marketplace.cdn.mozilla.net/img/uploads/previews/thumbs/88/88976.png?modified=1359738101", "image_url": "https://marketplace.cdn.mozilla.net/img/uploads/previews/full/88/88976.png?modified=1359738101", "id": "88976", "resource_uri": "/api/v1/apps/preview/88976/"}, {"filetype": "image/png", "caption": "Store", "thumbnail_url": "https://marketplace.cdn.mozilla.net/img/uploads/previews/thumbs/88/88978.png?modified=1359738101", "image_url": "https://marketplace.cdn.mozilla.net/img/uploads/previews/full/88/88978.png?modified=1359738101", "id": "88978", "resource_uri": "/api/v1/apps/preview/88978/"}, {"filetype": "image/png", "caption": "Score!", "thumbnail_url": "https://marketplace.cdn.mozilla.net/img/uploads/previews/thumbs/88/88980.png?modified=1359738103", "image_url": "https://marketplace.cdn.mozilla.net/img/uploads/previews/full/88/88980.png?modified=1359738103", "id": "88980", "resource_uri": "/api/v1/apps/preview/88980/"}, {"filetype": "image/png", "caption": "", "thumbnail_url": "https://marketplace.cdn.mozilla.net/img/uploads/previews/thumbs/88/88982.png?modified=1359738409", "image_url": "https://marketplace.cdn.mozilla.net/img/uploads/previews/full/88/88982.png?modified=1359738409", "id": "88982", "resource_uri": "/api/v1/apps/preview/88982/"}], "payment_account": null, "categories": [155], "supported_locales": [], "price_locale": null, "name": "Lunch Bug", "created": "2012-07-16T20:22:30", "device_types": ["desktop", "firefoxos"], "payment_required": false, "weekly_downloads": null, "image_assets": {"featured_tile": ["https://marketplace.cdn.mozilla.net/img/uploads/imageassets/2/2608.png?modified=1349796975", 0], "mobile_tile": ["https://marketplace.cdn.mozilla.net/img/uploads/imageassets/0/214.png?modified=1346968318", 0], "desktop_tile": ["https://marketplace.cdn.mozilla.net/img/uploads/imageassets/0/228.png?modified=1346968318", 0]}, "upsell": false, "resource_uri": "/api/v1/apps/app/383667/"}