{"premium_type": "free", "content_ratings": {"generic": [{"body": "Generic", "slug": "3", "description": "Not recommended for users younger than 3 years of age", "name": "3+", "body_slug": "generic"}], "br": [{"body": "CLASSIND", "slug": "0", "description": "General Audiences", "name": "0+", "body_slug": "classind"}]}, "manifest_url": "http://subjunglefrog.dseffects.com/JungleFrog.webapp", "current_version": "1", "upsold": null, "id": "404361", "ratings": {"count": 0, "average": 0.0}, "app_type": "hosted", "author": "DS Effects", "support_url": "http://www.dseffects.com", "slug": "junglefrog", "regions": [{"mcc": 722, "name": "Argentina", "adolescent": true, "slug": "ar"}, {"mcc": 724, "name": "Brazil", "adolescent": true, "slug": "br"}, {"mcc": 460, "name": "China", "adolescent": true, "slug": "cn"}, {"mcc": 732, "name": "Colombia", "adolescent": true, "slug": "co"}, {"mcc": 262, "name": "Germany", "adolescent": true, "slug": "de"}, {"mcc": 214, "name": "Spain", "adolescent": true, "slug": "es"}, {"mcc": 202, "name": "Greece", "adolescent": true, "slug": "gr"}, {"mcc": 216, "name": "Hungary", "adolescent": true, "slug": "hu"}, {"mcc": 297, "name": "Montenegro", "adolescent": true, "slug": "me"}, {"mcc": 334, "name": "Mexico", "adolescent": true, "slug": "mx"}, {"mcc": 716, "name": "Peru", "adolescent": true, "slug": "pe"}, {"mcc": 260, "name": "Poland", "adolescent": true, "slug": "pl"}, {"mcc": 220, "name": "Serbia", "adolescent": true, "slug": "rs"}, {"mcc": 235, "name": "United Kingdom", "adolescent": true, "slug": "uk"}, {"mcc": 310, "name": "United States", "adolescent": true, "slug": "us"}, {"mcc": 748, "name": "Uruguay", "adolescent": true, "slug": "uy"}, {"mcc": 734, "name": "Venezuela", "adolescent": true, "slug": "ve"}, {"mcc": null, "name": "Worldwide", "adolescent": true, "slug": "worldwide"}], "icons": {"16": "https://marketplace.cdn.mozilla.net/img/uploads/addon_icons/404/404361-32.png?modified=1382133449", "48": "https://marketplace.cdn.mozilla.net/img/uploads/addon_icons/404/404361-48.png?modified=1382133449", "128": "https://marketplace.cdn.mozilla.net/img/uploads/addon_icons/404/404361-128.png?modified=1382133449", "64": "https://marketplace.cdn.mozilla.net/img/uploads/addon_icons/404/404361-64.png?modified=1382133449"}, "created": "2012-10-24T05:05:16", "homepage": "", "support_email": "support@dseffects.com", "public_stats": false, "status": 4, "privacy_policy": "/api/v1/apps/app/404361/privacy/", "is_packaged": false, "description": "Jump from one branch to another and don't fall into the river. Touch the screen to set the jump power and release it to jump.", "default_locale": "en-US", "tags": [], "price": null, "previews": [{"filetype": "image/png", "thumbnail_url": "https://marketplace.cdn.mozilla.net/img/uploads/previews/thumbs/80/80717.png?modified=1351105582", "image_url": "https://marketplace.cdn.mozilla.net/img/uploads/previews/full/80/80717.png?modified=1351105582", "id": "80717", "resource_uri": "/api/v1/apps/preview/80717/"}, {"filetype": "image/png", "thumbnail_url": "https://marketplace.cdn.mozilla.net/img/uploads/previews/thumbs/80/80719.png?modified=1351105582", "image_url": "https://marketplace.cdn.mozilla.net/img/uploads/previews/full/80/80719.png?modified=1351105582", "id": "80719", "resource_uri": "/api/v1/apps/preview/80719/"}, {"filetype": "image/png", "thumbnail_url": "https://marketplace.cdn.mozilla.net/img/uploads/previews/thumbs/80/80721.png?modified=1351105582", "image_url": "https://marketplace.cdn.mozilla.net/img/uploads/previews/full/80/80721.png?modified=1351105582", "id": "80721", "resource_uri": "/api/v1/apps/preview/80721/"}], "payment_account": null, "categories": ["games"], "supported_locales": [], "price_locale": null, "name": "JungleFrog", "versions": {"1": "/api/v1/apps/versions/1390133/"}, "device_types": ["desktop", "android-mobile", "android-tablet", "firefoxos"], "payment_required": false, "weekly_downloads": null, "upsell": false, "resource_uri": "/api/v1/apps/app/404361/"}