{"premium_type": "free", "content_ratings": null, "manifest_url": "https://marketplace.firefox.com/app/5a5a3010-99e2-4b53-a85c-43a3c4bec21d/manifest.webapp", "current_version": "1.0", "upsold": null, "id": "433590", "ratings": {"count": 0, "average": 0.0}, "app_type": "packaged", "author": "onizuka89", "support_url": "", "slug": "kana", "regions": [{"mcc": 722, "name": "Argentina", "adolescent": true, "slug": "ar"}, {"mcc": 460, "name": "China", "adolescent": true, "slug": "cn"}, {"mcc": 732, "name": "Colombia", "adolescent": true, "slug": "co"}, {"mcc": 214, "name": "Spain", "adolescent": true, "slug": "es"}, {"mcc": 202, "name": "Greece", "adolescent": true, "slug": "gr"}, {"mcc": 716, "name": "Peru", "adolescent": true, "slug": "pe"}, {"mcc": 260, "name": "Poland", "adolescent": true, "slug": "pl"}, {"mcc": 748, "name": "Uruguay", "adolescent": true, "slug": "uy"}], "icons": {"16": "https://marketplace.cdn.mozilla.net/img/uploads/addon_icons/433/433590-32.png?modified=1373031935", "48": "https://marketplace.cdn.mozilla.net/img/uploads/addon_icons/433/433590-48.png?modified=1373031935", "128": "https://marketplace.cdn.mozilla.net/img/uploads/addon_icons/433/433590-128.png?modified=1373031935", "64": "https://marketplace.cdn.mozilla.net/img/uploads/addon_icons/433/433590-64.png?modified=1373031935"}, "created": "2013-04-23T06:49:40", "homepage": "", "support_email": "Onizuka89@gmail.com", "public_stats": false, "status": 4, "privacy_policy": "/api/v1/apps/app/433590/privacy/", "is_packaged": true, "description": "An app to practice reading kana.\nThe app is available for free until a system for charging is implemented in the marketplace.\nThis app is for those who are learning Japanese. \nSome of the features:\n<ul><li>Select which groups to practice</li><li>View your statistics</li><li>Reset your statistics</li></ul>", "default_locale": "en-US", "tags": [], "price": null, "previews": [{"filetype": "image/png", "thumbnail_url": "https://marketplace.cdn.mozilla.net/img/uploads/previews/thumbs/97/97638.png?modified=1366751040", "image_url": "https://marketplace.cdn.mozilla.net/img/uploads/previews/full/97/97638.png?modified=1366751040", "id": "97638", "resource_uri": "/api/v1/apps/preview/97638/"}, {"filetype": "image/png", "thumbnail_url": "https://marketplace.cdn.mozilla.net/img/uploads/previews/thumbs/97/97640.png?modified=1366751040", "image_url": "https://marketplace.cdn.mozilla.net/img/uploads/previews/full/97/97640.png?modified=1366751040", "id": "97640", "resource_uri": "/api/v1/apps/preview/97640/"}], "payment_account": null, "categories": ["education"], "supported_locales": [], "price_locale": null, "name": "Kana", "versions": {"0.1": "/api/v1/apps/versions/1443142/", "0.2": "/api/v1/apps/versions/1443172/", "1.0": "/api/v1/apps/versions/1446108/"}, "device_types": ["firefoxos"], "payment_required": false, "weekly_downloads": null, "upsell": false, "resource_uri": "/api/v1/apps/app/433590/"}