{"premium_type": "free", "content_ratings": null, "manifest_url": "http://jgmy.github.io/jigsawpuzzle/openwebapp/manifest.webapp", "current_version": "1.4.0.4", "upsold": null, "id": "436838", "ratings": {"count": 0, "average": 0.0}, "app_type": "hosted", "author": "Jose G Moya", "support_url": "http://josemoya.blogspot.com/2013/05/jigsawpuzzle-english-info-page.html", "slug": "jigsawpuzzle", "regions": [{"mcc": 722, "name": "Argentina", "adolescent": true, "slug": "ar"}, {"mcc": 460, "name": "China", "adolescent": true, "slug": "cn"}, {"mcc": 732, "name": "Colombia", "adolescent": true, "slug": "co"}, {"mcc": 214, "name": "Spain", "adolescent": true, "slug": "es"}, {"mcc": 202, "name": "Greece", "adolescent": true, "slug": "gr"}, {"mcc": 216, "name": "Hungary", "adolescent": true, "slug": "hu"}, {"mcc": 297, "name": "Montenegro", "adolescent": true, "slug": "me"}, {"mcc": 334, "name": "Mexico", "adolescent": true, "slug": "mx"}, {"mcc": 716, "name": "Peru", "adolescent": true, "slug": "pe"}, {"mcc": 260, "name": "Poland", "adolescent": true, "slug": "pl"}, {"mcc": 220, "name": "Serbia", "adolescent": true, "slug": "rs"}, {"mcc": 235, "name": "United Kingdom", "adolescent": true, "slug": "uk"}, {"mcc": 310, "name": "United States", "adolescent": true, "slug": "us"}, {"mcc": 748, "name": "Uruguay", "adolescent": true, "slug": "uy"}, {"mcc": 734, "name": "Venezuela", "adolescent": true, "slug": "ve"}, {"mcc": null, "name": "Worldwide", "adolescent": true, "slug": "worldwide"}], "icons": {"16": "https://marketplace.cdn.mozilla.net/img/uploads/addon_icons/436/436838-32.png?modified=1370038588", "48": "https://marketplace.cdn.mozilla.net/img/uploads/addon_icons/436/436838-48.png?modified=1370038588", "128": "https://marketplace.cdn.mozilla.net/img/uploads/addon_icons/436/436838-128.png?modified=1370038588", "64": "https://marketplace.cdn.mozilla.net/img/uploads/addon_icons/436/436838-64.png?modified=1370038588"}, "created": "2013-05-06T12:48:30", "homepage": "http://jgmy.github.io/jigsawpuzzle/", "support_email": "josemoya@gmail.com", "public_stats": false, "status": 4, "privacy_policy": "/api/v1/apps/app/436838/privacy/", "is_packaged": false, "description": "A Jigsaw Puzzle.\n\nThis is a simple jigsaw puzzle made with Scirra's Construct 2. You can select between two tilesets (48 pieces or 108 pieces) and three pictures (more pictures will be added in the future). You can select whether the pieces have black borders or not. You can switch between two different background colors or show the original image at background as hint.\nENGLISH:\nThis is a simple jigsaw puzzle made with Scirra's Construct 2. \nYou can select between two tilesets (48 pieces or 108 pieces) and three pictures (more pictures will be added in the future).\nYou can select whether the pieces have black borders or not.\nYou can switch between two different background colors or show the original image at background as hint.\n\nCOPYRIGHT INFO\nGame code, piece shapes and buttons are intellectual property of the author of this game (JGMY, <a href=\"http://outgoing.mozilla.org/v1/d194793d7cc9882219ef089977d7a80054066370769794307011b8d6658db2ab/http%3A//jmoysae.at.gmail.com\" rel=\"nofollow\">jmoysae.at.gmail.com</a>).\nSelectable puzzle pictures are took from different open media sites under open licenses. Author names and links to their licenses are provided.\nThis game was made with Scirra Construct2 and include Scirra's runtime, which includes code from different sources.", "default_locale": "en-US", "tags": [], "price": null, "previews": [{"filetype": "image/png", "thumbnail_url": "https://marketplace.cdn.mozilla.net/img/uploads/previews/thumbs/98/98856.png?modified=1367895855", "image_url": "https://marketplace.cdn.mozilla.net/img/uploads/previews/full/98/98856.png?modified=1367895855", "id": "98856", "resource_uri": "/api/v1/apps/preview/98856/"}], "payment_account": null, "categories": ["games"], "supported_locales": [], "price_locale": null, "name": "JigSawPuzzle", "versions": {"1.4.0.4": "/api/v1/apps/versions/1447472/"}, "device_types": ["desktop", "android-tablet"], "payment_required": false, "weekly_downloads": null, "upsell": false, "resource_uri": "/api/v1/apps/app/436838/"}