{"premium_type": "free", "content_ratings": null, "manifest_url": "https://marketplace-dev.allizom.org/app/acfde257-4cbf-4356-8f88-bf976a44e525/manifest.webapp", "current_version": "2.0", "upsold": null, "id": "458674", "ratings": {"count": 0, "average": 0.0}, "app_type": "packaged", "author": "Dharwin Aaron Perez Rodriguez", "support_url": "http://dharwinperez.com", "slug": "turiapp", "regions": [{"mcc": 722, "name": "Argentina", "adolescent": true, "slug": "ar"}, {"mcc": 724, "name": "Brazil", "adolescent": true, "slug": "br"}, {"mcc": 460, "name": "China", "adolescent": true, "slug": "cn"}, {"mcc": 732, "name": "Colombia", "adolescent": true, "slug": "co"}, {"mcc": 262, "name": "Germany", "adolescent": true, "slug": "de"}, {"mcc": 214, "name": "Spain", "adolescent": true, "slug": "es"}, {"mcc": 202, "name": "Greece", "adolescent": true, "slug": "gr"}, {"mcc": 216, "name": "Hungary", "adolescent": true, "slug": "hu"}, {"mcc": 297, "name": "Montenegro", "adolescent": true, "slug": "me"}, {"mcc": 334, "name": "Mexico", "adolescent": true, "slug": "mx"}, {"mcc": 716, "name": "Peru", "adolescent": true, "slug": "pe"}, {"mcc": 260, "name": "Poland", "adolescent": true, "slug": "pl"}, {"mcc": 220, "name": "Serbia", "adolescent": true, "slug": "rs"}, {"mcc": 235, "name": "United Kingdom", "adolescent": true, "slug": "uk"}, {"mcc": 310, "name": "United States", "adolescent": true, "slug": "us"}, {"mcc": 748, "name": "Uruguay", "adolescent": true, "slug": "uy"}, {"mcc": 734, "name": "Venezuela", "adolescent": true, "slug": "ve"}, {"mcc": null, "name": "Worldwide", "adolescent": true, "slug": "worldwide"}], "icons": {"16": "https://marketplace-dev-cdn.allizom.org/img/uploads/addon_icons/458/458674-32.png?modified=1375841983", "48": "https://marketplace-dev-cdn.allizom.org/img/uploads/addon_icons/458/458674-48.png?modified=1375841983", "128": "https://marketplace-dev-cdn.allizom.org/img/uploads/addon_icons/458/458674-128.png?modified=1375841983", "64": "https://marketplace-dev-cdn.allizom.org/img/uploads/addon_icons/458/458674-64.png?modified=1375841983"}, "created": "2013-08-03T00:14:56", "homepage": "", "support_email": "yo@dharwinperez.com", "public_stats": false, "status": 4, "privacy_policy": "/api/v1/apps/app/458674/privacy/", "is_packaged": true, "description": "TuriApp es una aplicaci\u00f3n enfocada a los recidentes y turistas del D.F., que permite localizar los sitios turisticos m\u00e1s importantes y cercanos a la zona en la que se encuentran", "default_locale": "es", "price": null, "previews": [{"filetype": "image/png", "thumbnail_url": "https://marketplace-dev-cdn.allizom.org/img/uploads/previews/thumbs/110/110401.png?modified=1375841984", "image_url": "https://marketplace-dev-cdn.allizom.org/img/uploads/previews/full/110/110401.png?modified=1375841984", "id": "110401", "resource_uri": "/api/v1/apps/preview/110401/"}, {"filetype": "image/png", "thumbnail_url": "https://marketplace-dev-cdn.allizom.org/img/uploads/previews/thumbs/110/110402.png?modified=1375841984", "image_url": "https://marketplace-dev-cdn.allizom.org/img/uploads/previews/full/110/110402.png?modified=1375841984", "id": "110402", "resource_uri": "/api/v1/apps/preview/110402/"}, {"filetype": "image/png", "thumbnail_url": "https://marketplace-dev-cdn.allizom.org/img/uploads/previews/thumbs/110/110403.png?modified=1375841984", "image_url": "https://marketplace-dev-cdn.allizom.org/img/uploads/previews/full/110/110403.png?modified=1375841984", "id": "110403", "resource_uri": "/api/v1/apps/preview/110403/"}], "payment_account": null, "categories": ["entertainment", "travel"], "supported_locales": [], "price_locale": null, "name": "TuriApp", "versions": {"2.0": "/api/v1/apps/versions/1481162/", "1.1": "/api/v1/apps/versions/1480927/"}, "device_types": ["firefoxos"], "payment_required": false, "weekly_downloads": null, "upsell": false, "resource_uri": "/api/v1/apps/app/458674/"}