{"premium_type": "free", "content_ratings": null, "manifest_url": "https://marketplace.firefox.com/app/9b62ee2b-0037-4101-afbf-758471dcf9f4/manifest.webapp", "current_version": "1.0", "upsold": null, "id": "461837", "ratings": {"count": 3, "average": 1.6667000000000001}, "app_type": "packaged", "author": "lihattv.com", "support_url": "http://lihattv.com", "slug": "lihattv", "regions": [{"mcc": 722, "name": "Argentina", "adolescent": true, "slug": "ar"}, {"mcc": 724, "name": "Brazil", "adolescent": true, "slug": "br"}, {"mcc": 460, "name": "China", "adolescent": true, "slug": "cn"}, {"mcc": 732, "name": "Colombia", "adolescent": true, "slug": "co"}, {"mcc": 262, "name": "Germany", "adolescent": true, "slug": "de"}, {"mcc": 214, "name": "Spain", "adolescent": true, "slug": "es"}, {"mcc": 202, "name": "Greece", "adolescent": true, "slug": "gr"}, {"mcc": 216, "name": "Hungary", "adolescent": true, "slug": "hu"}, {"mcc": 297, "name": "Montenegro", "adolescent": true, "slug": "me"}, {"mcc": 334, "name": "Mexico", "adolescent": true, "slug": "mx"}, {"mcc": 716, "name": "Peru", "adolescent": true, "slug": "pe"}, {"mcc": 260, "name": "Poland", "adolescent": true, "slug": "pl"}, {"mcc": 220, "name": "Serbia", "adolescent": true, "slug": "rs"}, {"mcc": 235, "name": "United Kingdom", "adolescent": true, "slug": "uk"}, {"mcc": 310, "name": "United States", "adolescent": true, "slug": "us"}, {"mcc": 748, "name": "Uruguay", "adolescent": true, "slug": "uy"}, {"mcc": 734, "name": "Venezuela", "adolescent": true, "slug": "ve"}, {"mcc": null, "name": "Worldwide", "adolescent": true, "slug": "worldwide"}], "icons": {"16": "https://marketplace.cdn.mozilla.net/img/uploads/addon_icons/461/461837-32.png?modified=1381502486", "48": "https://marketplace.cdn.mozilla.net/img/uploads/addon_icons/461/461837-48.png?modified=1381502486", "128": "https://marketplace.cdn.mozilla.net/img/uploads/addon_icons/461/461837-128.png?modified=1381502486", "64": "https://marketplace.cdn.mozilla.net/img/uploads/addon_icons/461/461837-64.png?modified=1381502486"}, "created": "2013-08-27T08:22:59", "homepage": "http://lihattv.com", "support_email": "info@lihattv.us", "public_stats": true, "status": 4, "privacy_policy": "/api/v1/apps/app/461837/privacy/", "is_packaged": true, "description": "Watch free TV for PC and Mobile device.\nlihattv will make Firefox OS to be able watching live tv streaming.\n\nDaily update live tv with support for\n- Web (Windows, Linux, Mac, other)\n- Smart Phones (Symbian, Blackberry, Android, Windows, Firefox, iOS)\n- Media Player (VLC, KMPlayer, SMPlayer, SPlayer, SimpleTV, TorrentStream, Winamp, Windows Media Player, Daum PotPlayer, RealPlayer, JRiver Media Center, others)\n- Media Centre (XBMC, PlayOn)\n- Set Top Box (Boxee Box, LG SmartTV, Android TV Box)", "default_locale": "en-US", "tags": [], "price": null, "previews": [{"filetype": "image/png", "thumbnail_url": "https://marketplace.cdn.mozilla.net/img/uploads/previews/thumbs/113/113729.png?modified=1379963503", "image_url": "https://marketplace.cdn.mozilla.net/img/uploads/previews/full/113/113729.png?modified=1379963503", "id": "113729", "resource_uri": "/api/v1/apps/preview/113729/"}, {"filetype": "image/png", "thumbnail_url": "https://marketplace.cdn.mozilla.net/img/uploads/previews/thumbs/113/113730.png?modified=1379963503", "image_url": "https://marketplace.cdn.mozilla.net/img/uploads/previews/full/113/113730.png?modified=1379963503", "id": "113730", "resource_uri": "/api/v1/apps/preview/113730/"}, {"filetype": "image/png", "thumbnail_url": "https://marketplace.cdn.mozilla.net/img/uploads/previews/thumbs/113/113731.png?modified=1379963504", "image_url": "https://marketplace.cdn.mozilla.net/img/uploads/previews/full/113/113731.png?modified=1379963504", "id": "113731", "resource_uri": "/api/v1/apps/preview/113731/"}], "payment_account": null, "categories": ["entertainment", "productivity"], "supported_locales": [], "price_locale": null, "name": "tvQu Online", "versions": {"0.1": "/api/v1/apps/versions/1485065/", "1.0": "/api/v1/apps/versions/1490057/"}, "device_types": ["android-mobile", "android-tablet", "firefoxos"], "payment_required": false, "weekly_downloads": 0, "upsell": false, "resource_uri": "/api/v1/apps/app/461837/"}