{"app_type": "hosted", "author": "Radgost", "categories": ["business", "utilities"], "content_ratings": {"ratings": null, "interactive_elements": null, "descriptors": null}, "created": "2013-02-02T13:50:55", "current_version": "1.0", "default_locale": "en-US", "device_types": ["desktop", "android-mobile", "android-tablet", "firefoxos"], "description": {"en-US": "Online Invoicing App\nThe fastest way to online invoicing."}, "homepage": {"en-US": "http://invoiceocean.com"}, "icons": {"16": "https://marketplace.cdn.mozilla.net/img/uploads/addon_icons/419/419794-32.png?modified=1377555006", "48": "https://marketplace.cdn.mozilla.net/img/uploads/addon_icons/419/419794-48.png?modified=1377555006", "128": "https://marketplace.cdn.mozilla.net/img/uploads/addon_icons/419/419794-128.png?modified=1377555006", "64": "https://marketplace.cdn.mozilla.net/img/uploads/addon_icons/419/419794-64.png?modified=1377555006"}, "id": 419794, "is_packaged": false, "manifest_url": "http://invoiceocean.com/config/invoiceocean/manifest.webapp", "name": {"en-US": "InvoiceOcean"}, "payment_account": null, "payment_required": false, "premium_type": "free", "previews": [{"filetype": "image/png", "image_url": "https://marketplace.cdn.mozilla.net/img/uploads/previews/full/89/89106.png?modified=1361876631", "id": 89106, "resource_uri": null, "thumbnail_url": "https://marketplace.cdn.mozilla.net/img/uploads/previews/thumbs/89/89106.png?modified=1361876631"}, {"filetype": "image/png", "image_url": "https://marketplace.cdn.mozilla.net/img/uploads/previews/full/91/91396.png?modified=1361905434", "id": 91396, "resource_uri": null, "thumbnail_url": "https://marketplace.cdn.mozilla.net/img/uploads/previews/thumbs/91/91396.png?modified=1361905434"}], "price": null, "price_locale": null, "privacy_policy": "/api/v1/apps/app/419794/privacy/", "public_stats": false, "ratings": {"count": 0, "average": 0.0}, "regions": [{"name": "Argentina", "slug": "ar", "mcc": 722, "adolescent": true}, {"name": "Brazil", "slug": "br", "mcc": 724, "adolescent": true}, {"name": "Colombia", "slug": "co", "mcc": 732, "adolescent": true}, {"name": "Germany", "slug": "de", "mcc": 262, "adolescent": true}, {"name": "Spain", "slug": "es", "mcc": 214, "adolescent": true}, {"name": "Greece", "slug": "gr", "mcc": 202, "adolescent": true}, {"name": "Hungary", "slug": "hu", "mcc": 216, "adolescent": true}, {"name": "Italy", "slug": "it", "mcc": 222, "adolescent": true}, {"name": "Montenegro", "slug": "me", "mcc": 297, "adolescent": true}, {"name": "Mexico", "slug": "mx", "mcc": 334, "adolescent": true}, {"name": "Peru", "slug": "pe", "mcc": 716, "adolescent": true}, {"name": "Poland", "slug": "pl", "mcc": 260, "adolescent": true}, {"name": "Serbia", "slug": "rs", "mcc": 220, "adolescent": true}, {"name": "United Kingdom", "slug": "uk", "mcc": 235, "adolescent": true}, {"name": "United States", "slug": "us", "mcc": 310, "adolescent": true}, {"name": "Uruguay", "slug": "uy", "mcc": 748, "adolescent": true}, {"name": "Venezuela", "slug": "ve", "mcc": 734, "adolescent": true}, {"name": "Worldwide", "slug": "worldwide", "mcc": null, "adolescent": true}], "release_notes": null, "resource_uri": "/api/v1/apps/app/419794/", "slug": "invoiceocean", "status": 4, "summary": null, "support_email": {"en-US": "helpdesk@invoiceocean.com"}, "support_url": {"en-US": "http://help.invoiceocean.com"}, "supported_locales": [], "tags": [], "upsell": false, "upsold": null, "user": null, "versions": {"1.0": "/api/v1/apps/versions/1418430/"}, "weekly_downloads": null, "guid": "6756d271-6205-4d3c-868a-a589bd58efae", "app_slug": "invoiceocean", "type": 11, "highest_status": 4, "icon_type": "image/png", "developer_comments": null, "eula": null, "the_reason": null, "the_future": null, "average_rating": 0.0, "bayesian_rating": 0.0, "total_reviews": 0, "total_downloads": 0, "hotness": 0.0, "average_daily_downloads": 0, "average_daily_users": 0, "share_count": 0, "disabled_by_user": false, "trusted": false, "view_source": true, "prerelease": false, "admin_review": false, "admin_review_type": 1, "site_specific": false, "external_software": false, "dev_agreement": false, "auto_repackage": true, "outstanding": false, "target_locale": null, "locale_disambiguation": null, "wants_contributions": false, "paypal_id": "", "suggested_amount": null, "total_contributions": null, "annoying": 0, "enable_thankyou": false, "thankyou_note": null, "app_domain": "http://invoiceocean.com", "mozilla_contact": "", "enable_new_regions": true, "authors": [6257191], "dependencies": []}